06_instruction_memory/instruction_memory.v
module instruction_memory(
    input [7:0] address,
    output [7:0] instruction 
);

reg [7:0] memory [0:7];

initial begin
    memory[0] = 8'b00010001;
    memory[1] = 8'b00100010;
    memory[2] = 8'b00110011;
    memory[3] = 8'b01000100;
    memory[4] = 8'b01010101;
    memory[5] = 8'b01100110;
    memory[6] = 8'b01110111;
    memory[7] = 8'b10001000;
end

assign instruction = memory[address];


endmodule

06_instruction_memory/instruction_memory_tb.v
`timescale 1ns/1ps

module instruction_memory_tb;

reg [7:0] address;
wire [7:0] instruction_out;

instruction_memory uut(
    .address(address),
    .instruction(instruction_out)

);

initial begin 
    $dumpfile("instruction_memory.vcd"); 
    $dumpvars(0, instruction_memory_tb);
    
    address=0;
    #10;

    address=1;
    #10;

    address=2;
    #10;

    address=3;
    #10;

    address=4;
    #10;

    address=5;
    #10;
    
    address=6;
    #10;

    address=7;
    #10;

    $finish;

end

endmodule

06_instruction_memory/instruction_memory.vcd
$date
	Mon Sep  7 22:40:21 2026
$end
$version
	Icarus Verilog
$end
$timescale
	1ps
$end
$scope module instruction_memory_tb $end
$var wire 8 ! instruction_out [7:0] $end
$var reg 8 " address [7:0] $end
$scope module uut $end
$var wire 8 # address [7:0] $end
$var wire 8 $ instruction [7:0] $end
$upscope $end
$upscope $end
$enddefinitions $end
$comment Show the parameter values. $end
$dumpall
$end
#0
$dumpvars
b10001 $
b0 #
b0 "
b10001 !
$end
#10000
b100010 !
b100010 $
b1 "
b1 #
#20000
b110011 !
b110011 $
b10 "
b10 #
#30000
b1000100 !
b1000100 $
b11 "
b11 #
#40000
b1010101 !
b1010101 $
b100 "
b100 #
#50000
b1100110 !
b1100110 $
b101 "
b101 #
#60000
b1110111 !
b1110111 $
b110 "
b110 #
#70000
b10001000 !
b10001000 $
b111 "
b111 #
